[
  {
    "title": "刀際效應-每週三海期盤勢經驗分享(2026/03)2026/03/11 2000~2030價格NT：2000",
    "url": "https://www.staraca.com/chinese/edu//chinese/edu/educon.asp?ID=4138"
  },
  {
    "title": "海期實戰教室(線上)一個月期(2603)2026/03/11 2100~2355價格NT：10000",
    "url": "https://www.staraca.com/chinese/edu//chinese/edu/educon.asp?ID=4276"
  },
  {
    "title": "凱子小刀量化機器人課程(6個月期)2026/03/31 0000~2359價格NT：48000",
    "url": "https://www.staraca.com/chinese/edu//chinese/edu/educon.asp?ID=4476"
  },
  {
    "title": "刀派手單台指期專修課2026/03/31 0000~2359價格NT：12000",
    "url": "https://www.staraca.com/chinese/edu//chinese/edu/educon.asp?ID=4477"
  },
  {
    "title": "刀派期權實戰必備戰技2026/03/31 0000~2359價格NT：13500",
    "url": "https://www.staraca.com/chinese/edu//chinese/edu/educon.asp?ID=4472"
  },
  {
    "title": "我是交易員2026/03/31 0000~2359價格NT：8000",
    "url": "https://www.staraca.com/chinese/edu//chinese/edu/educon.asp?ID=4470"
  },
  {
    "title": "刀際效應-每週三海期盤勢經驗分享(2026/04)2026/04/01 2000~2030價格NT：2000",
    "url": "https://www.staraca.com/chinese/edu//chinese/edu/educon.asp?ID=4321"
  },
  {
    "title": "海期實戰教室(線上)一個月期(2604)2026/04/01 2100~2355價格NT：10000",
    "url": "https://www.staraca.com/chinese/edu//chinese/edu/educon.asp?ID=4341"
  },
  {
    "title": "海期實戰教室(線上)一個月期(2605)2026/05/01 2100~2355價格NT：10000",
    "url": "https://www.staraca.com/chinese/edu//chinese/edu/educon.asp?ID=4342"
  },
  {
    "title": "刀際效應-每週三海期盤勢經驗分享(2026/05)2026/05/06 2000~2030價格NT：2000",
    "url": "https://www.staraca.com/chinese/edu//chinese/edu/educon.asp?ID=4325"
  },
  {
    "title": "海期實戰教室(線上)一個月期(2606)2026/06/01 2100~2355價格NT：10000",
    "url": "https://www.staraca.com/chinese/edu//chinese/edu/educon.asp?ID=4343"
  },
  {
    "title": "刀際效應-每週三海期盤勢經驗分享(2026/06)2026/06/03 2000~2030價格NT：2000",
    "url": "https://www.staraca.com/chinese/edu//chinese/edu/educon.asp?ID=4326"
  },
  {
    "title": "刀際效應-每週三海期盤勢經驗分享(2026/07)2026/07/01 2000~2030價格NT：2000",
    "url": "https://www.staraca.com/chinese/edu//chinese/edu/educon.asp?ID=4327"
  },
  {
    "title": "海期實戰教室(線上)一個月期(2607)2026/07/01 2100~2355價格NT：10000",
    "url": "https://www.staraca.com/chinese/edu//chinese/edu/educon.asp?ID=4344"
  },
  {
    "title": "海期實戰教室(線上)一個月期(2608)2026/08/03 2100~2355價格NT：10000",
    "url": "https://www.staraca.com/chinese/edu//chinese/edu/educon.asp?ID=4345"
  },
  {
    "title": "刀際效應-每週三海期盤勢經驗分享(2026/08)2026/08/05 2000~2030價格NT：2000",
    "url": "https://www.staraca.com/chinese/edu//chinese/edu/educon.asp?ID=4328"
  },
  {
    "title": "刀際效應-每週三海期盤勢經驗分享(2026/09)2026/09/02 2000~2030價格NT：2000",
    "url": "https://www.staraca.com/chinese/edu//chinese/edu/educon.asp?ID=4329"
  },
  {
    "title": "海期實戰教室(線上)一個月期(2609)2026/09/02 2100~2355價格NT：10000",
    "url": "https://www.staraca.com/chinese/edu//chinese/edu/educon.asp?ID=4346"
  },
  {
    "title": "海期實戰教室(線上)一個月期(2610)2026/10/02 2100~2355價格NT：10000",
    "url": "https://www.staraca.com/chinese/edu//chinese/edu/educon.asp?ID=4347"
  },
  {
    "title": "刀際效應-每週三海期盤勢經驗分享(2026/10)2026/10/07 2000~2030價格NT：2000",
    "url": "https://www.staraca.com/chinese/edu//chinese/edu/educon.asp?ID=4330"
  },
  {
    "title": "刀際效應-每週三海期盤勢經驗分享(2026/11)2026/11/04 2000~2030價格NT：2000",
    "url": "https://www.staraca.com/chinese/edu//chinese/edu/educon.asp?ID=4355"
  },
  {
    "title": "刀際效應-每週三海期盤勢經驗分享(2026/12)2026/12/02 2000~2030價格NT：2000",
    "url": "https://www.staraca.com/chinese/edu//chinese/edu/educon.asp?ID=4356"
  },
  {
    "title": "刀際效應-每週三海期盤勢經驗分享(2027/01)2027/01/06 2000~2030價格NT：2000",
    "url": "https://www.staraca.com/chinese/edu//chinese/edu/educon.asp?ID=4357"
  }
]